survey_technical_requirements/__init__.py
survey_technical_requirements/main.py
xgh_survey_technical_requirements-0.0.0.dist-info/LICENSE
xgh_survey_technical_requirements-0.0.0.dist-info/METADATA
xgh_survey_technical_requirements-0.0.0.dist-info/WHEEL
xgh_survey_technical_requirements-0.0.0.dist-info/entry_points.txt
xgh_survey_technical_requirements-0.0.0.dist-info/top_level.txt
xgh_survey_technical_requirements-0.0.0.dist-info/RECORD
