Metadata-Version: 2.1
Name: xgh-survey-technical-requirements
Version: 0.0.0
Summary: 生成勘察报告技术要求
Home-page: UNKNOWN
Author: xgh
License: UNKNOWN
Platform: UNKNOWN
License-File: LICENSE
